{
    "meta": {
        "limit": 1000,
        "next": null,
        "offset": 0,
        "previous": null,
        "total_count": 3
    },
    "objects": [
        {
            "absentee_and_provisional": false,
            "cong_dist_level": false,
            "cong_dist_level_status": "",
            "county_level": true,
            "county_level_status": "",
            "direct_link": "",
            "direct_links": [
                "http://www.azsos.gov/election/2008/General/Canvass2008GE.pdf"
            ],
            "end_date": "2008-11-04",
            "gov": false,
            "house": true,
            "id": 9,
            "organization": {
                "city": "Phoenix",
                "fec_page": "",
                "gov_agency": true,
                "gov_level": "state",
                "id": 24,
                "name": "Arizona Secretary of State",
                "resource_uri": "/api/v1/organization/24/",
                "slug": "arizona-secretary-state",
                "state": "AZ",
                "street": "1700 W. Washington St. ",
                "url": "http://www.azsos.gov/"
            },
            "portal_link": "http://www.azsos.gov/election/2008/General/ElectionInformation.htm",
            "precinct_level": true,
            "precinct_level_status": "",
            "prez": true,
            "primary_note": "",
            "primary_type": "",
            "race_type": "general",
            "resource_uri": "/api/v1/election/9/",
            "result_type": "certified",
            "senate": true,
            "special": false,
            "start_date": "2008-11-04",
            "state": {
                "name": "Arizona",
                "postal": "AZ",
                "resource_uri": "/api/v1/state/AZ/"
            },
            "state_leg": true,
            "state_leg_level": false,
            "state_leg_level_status": "",
            "state_level": false,
            "state_level_status": "",
            "state_officers": false,
            "user_fullname": "Wyloge, Evan "
        },
        {
            "absentee_and_provisional": false,
            "cong_dist_level": false,
            "cong_dist_level_status": "",
            "county_level": true,
            "county_level_status": "",
            "direct_link": "",
            "direct_links": [
                "http://www.azsos.gov/election/2008/Primary/Canvass2008PE.pdf"
            ],
            "end_date": "2008-09-02",
            "gov": false,
            "house": true,
            "id": 10,
            "organization": {
                "city": "Phoenix",
                "fec_page": "",
                "gov_agency": true,
                "gov_level": "state",
                "id": 24,
                "name": "Arizona Secretary of State",
                "resource_uri": "/api/v1/organization/24/",
                "slug": "arizona-secretary-state",
                "state": "AZ",
                "street": "1700 W. Washington St. ",
                "url": "http://www.azsos.gov/"
            },
            "portal_link": "http://www.azsos.gov/election/2008/Primary/ElectionInformation.htm",
            "precinct_level": true,
            "precinct_level_status": "",
            "prez": false,
            "primary_note": "",
            "primary_type": "closed",
            "race_type": "primary",
            "resource_uri": "/api/v1/election/10/",
            "result_type": "certified",
            "senate": true,
            "special": false,
            "start_date": "2008-09-02",
            "state": {
                "name": "Arizona",
                "postal": "AZ",
                "resource_uri": "/api/v1/state/AZ/"
            },
            "state_leg": true,
            "state_leg_level": false,
            "state_leg_level_status": "",
            "state_level": false,
            "state_level_status": "",
            "state_officers": false,
            "user_fullname": "Wyloge, Evan "
        },
        {
            "absentee_and_provisional": false,
            "cong_dist_level": true,
            "cong_dist_level_status": "yes",
            "county_level": false,
            "county_level_status": "yes",
            "direct_link": "http://www.azsos.gov/ftp/dbelec/2008/ppe/eresults.csv",
            "direct_links": [
                "http://www.azsos.gov/election/2008/Primary/Canvass2008PE.pdf"
            ],
            "end_date": "2008-02-05",
            "gov": false,
            "house": false,
            "id": 11,
            "organization": {
                "city": "Phoenix",
                "fec_page": "",
                "gov_agency": true,
                "gov_level": "state",
                "id": 24,
                "name": "Arizona Secretary of State",
                "resource_uri": "/api/v1/organization/24/",
                "slug": "arizona-secretary-state",
                "state": "AZ",
                "street": "1700 W. Washington St. ",
                "url": "http://www.azsos.gov/"
            },
            "portal_link": "http://www.azsos.gov/election/2008/Primary/ElectionInformation.htm",
            "precinct_level": false,
            "precinct_level_status": "yes",
            "prez": true,
            "primary_note": "",
            "primary_type": "closed",
            "race_type": "primary",
            "resource_uri": "/api/v1/election/11/",
            "result_type": "certified",
            "senate": false,
            "special": false,
            "start_date": "2008-02-05",
            "state": {
                "name": "Arizona",
                "postal": "AZ",
                "resource_uri": "/api/v1/state/AZ/"
            },
            "state_leg": false,
            "state_leg_level": false,
            "state_leg_level_status": "no",
            "state_level": true,
            "state_level_status": "yes",
            "state_officers": false,
            "user_fullname": "Wyloge, Evan "
        }
    ]
}