{
    "meta": {
        "limit": 1000,
        "next": null,
        "offset": 0,
        "previous": null,
        "total_count": 3
    },
    "objects": [
        {
            "absentee_and_provisional": true,
            "cong_dist_level": false,
            "cong_dist_level_status": "",
            "county_level": false,
            "county_level_status": "",
            "direct_link": "http://www.dcboee.org/election_info/election_results/elec_2004/pres_general_2004_results.asp",
            "direct_links": [
                "https://www.dcboee.org/election_info/election_results/elec_2004/pres_general_2004_results.asp",
                "https://www.dcboee.org/pdf_files/Summary_2.pdf",
                "https://www.dcboee.org/pdf_files/Ward_Report_Nov2.pdf",
                "https://www.dcboee.org/pdf_files/Precinct_Report_Nov2.pdf"
            ],
            "end_date": "2004-11-02",
            "gov": false,
            "house": true,
            "id": 90,
            "organization": {
                "city": "",
                "fec_page": "",
                "gov_agency": true,
                "gov_level": "state",
                "id": 1,
                "name": "DC Board of Ethics and Elections",
                "resource_uri": "/api/v1/organization/1/",
                "slug": "dc-board-ethics-and-elections",
                "state": "DC",
                "street": "",
                "url": ""
            },
            "portal_link": "http://www.dcboee.org/election_info/election_results/",
            "precinct_level": true,
            "precinct_level_status": "yes",
            "prez": true,
            "primary_note": "",
            "primary_type": "",
            "race_type": "general",
            "resource_uri": "/api/v1/election/90/",
            "result_type": "certified",
            "senate": false,
            "special": false,
            "start_date": "2004-11-02",
            "state": {
                "name": "District of Columbia",
                "postal": "DC",
                "resource_uri": "/api/v1/state/DC/"
            },
            "state_leg": false,
            "state_leg_level": false,
            "state_leg_level_status": "",
            "state_level": true,
            "state_level_status": "yes",
            "state_officers": false,
            "user_fullname": "Admin, OpenElexUser"
        },
        {
            "absentee_and_provisional": true,
            "cong_dist_level": false,
            "cong_dist_level_status": "",
            "county_level": false,
            "county_level_status": "",
            "direct_link": "",
            "direct_links": [
                "https://www.dcboee.org/election_info/election_results/elec_2004/cong_citycouncil_2004_results.asp",
                "https://www.dcboee.org/pdf_files/14Sep2004_Certified_Summary_Report.pdf",
                "https://www.dcboee.org/pdf_files/14Sep2004_Precinct_Report.pdf",
                "https://www.dcboee.org/pdf_files/14Sep2004_Certified_Precinct_Turnout_Report.pdf",
                "https://www.dcboee.org/election_info/election_results/elec_2004/Statement_of_Vote.xls"
            ],
            "end_date": "2004-09-14",
            "gov": false,
            "house": true,
            "id": 1476,
            "organization": {
                "city": "",
                "fec_page": "",
                "gov_agency": true,
                "gov_level": "state",
                "id": 1,
                "name": "DC Board of Ethics and Elections",
                "resource_uri": "/api/v1/organization/1/",
                "slug": "dc-board-ethics-and-elections",
                "state": "DC",
                "street": "",
                "url": ""
            },
            "portal_link": "http://www.dcboee.org/election_info/election_results/",
            "precinct_level": true,
            "precinct_level_status": "yes",
            "prez": false,
            "primary_note": "",
            "primary_type": "closed",
            "race_type": "primary",
            "resource_uri": "/api/v1/election/1476/",
            "result_type": "certified",
            "senate": true,
            "special": false,
            "start_date": "2004-09-14",
            "state": {
                "name": "District of Columbia",
                "postal": "DC",
                "resource_uri": "/api/v1/state/DC/"
            },
            "state_leg": true,
            "state_leg_level": false,
            "state_leg_level_status": "",
            "state_level": true,
            "state_level_status": "yes",
            "state_officers": false,
            "user_fullname": ""
        },
        {
            "absentee_and_provisional": true,
            "cong_dist_level": false,
            "cong_dist_level_status": "",
            "county_level": false,
            "county_level_status": "",
            "direct_link": "",
            "direct_links": [
                "https://www.dcboee.org/election_info/election_results/elec_2004/pres_primary_2004_results.asp",
                "https://www.dcboee.org/pdf_files/ey2004_presprimary_summary.pdf",
                "https://www.dcboee.org/pdf_files/ey2004_presprimary_precinct.pdf"
            ],
            "end_date": "2004-01-13",
            "gov": false,
            "house": false,
            "id": 1477,
            "organization": {
                "city": "",
                "fec_page": "",
                "gov_agency": true,
                "gov_level": "state",
                "id": 1,
                "name": "DC Board of Ethics and Elections",
                "resource_uri": "/api/v1/organization/1/",
                "slug": "dc-board-ethics-and-elections",
                "state": "DC",
                "street": "",
                "url": ""
            },
            "portal_link": "http://www.dcboee.org/election_info/election_results/",
            "precinct_level": true,
            "precinct_level_status": "yes",
            "prez": true,
            "primary_note": "",
            "primary_type": "closed",
            "race_type": "primary",
            "resource_uri": "/api/v1/election/1477/",
            "result_type": "certified",
            "senate": false,
            "special": false,
            "start_date": "2004-01-13",
            "state": {
                "name": "District of Columbia",
                "postal": "DC",
                "resource_uri": "/api/v1/state/DC/"
            },
            "state_leg": false,
            "state_leg_level": false,
            "state_leg_level_status": "",
            "state_level": true,
            "state_level_status": "yes",
            "state_officers": false,
            "user_fullname": ""
        }
    ]
}